{"matplotlib.pyplot.imshow": ["matplotlib.pyplot.gca", "warnings.warn", "matplotlib.pyplot.sci"], "matplotlib.pyplot.text": ["matplotlib.pyplot.gca"], "matplotlib.pyplot.figure": ["matplotlib.pyplot.get_fignums", "<builtin>.max", "<builtin>.isinstance", "matplotlib.pyplot.get_figlabels", "<builtin>.int", "warnings.warn", "matplotlib.is_interactive", "<builtin>.len", "matplotlib.get_backend"], "matplotlib.pyplot.gca": ["matplotlib.pyplot.gcf"], "matplotlib.pyplot.sci": ["matplotlib.pyplot.gca"], "matplotlib.pyplot.get_fignums": ["<builtin>.sorted"], "matplotlib.pyplot.gcf": ["matplotlib.pyplot.figure"]}