{"<builtin>": ["<builtin>.locals", "<builtin>.isinstance", "<builtin>.bool", "<builtin>.ValueError", "<builtin>.callable", "<builtin>.len", "<builtin>.sorted", "<builtin>.set", "<builtin>.type", "<builtin>.NotImplementedError", "<builtin>.AssertionError", "<builtin>.int", "<builtin>.next", "<builtin>.iter", "<builtin>.getattr", "<builtin>.hasattr", "<builtin>.list", "<builtin>.range", "<builtin>.float", "<builtin>.TypeError", "<builtin>.dict", "<builtin>.slice", "<builtin>.all", "<builtin>.tuple", "<builtin>.repr", "<builtin>.ord", "<builtin>.enumerate", "<builtin>.issubclass", "<builtin>.any", "<builtin>.zip", "<builtin>.map", "<builtin>.hash", "<builtin>.sum", "<builtin>.str", "<builtin>.OverflowError", "<builtin>.id", "<builtin>.super", "<builtin>.max", "<builtin>.KeyError", "<builtin>.abs", "<builtin>.IndexError"], "functools": ["functools.partial"], "typing": ["typing.cast"], "numpy": ["numpy.array", "numpy.any", "numpy.asarray", "numpy.dtype", "numpy.min", "numpy.zeros", "numpy.errstate", "numpy.ma.getdata", "numpy.ma.getmaskarray", "numpy.empty", "numpy.timedelta64", "numpy.full", "numpy.arange", "numpy.all", "numpy.array_equal", "numpy.isfinite", "numpy.isnan", "numpy.vstack", "numpy.atleast_2d", "numpy.min_scalar_type", "numpy.promote_types", "numpy.can_cast", "numpy.round", "numpy.ndim", "numpy.where", "numpy.ones", "numpy.concatenate", "numpy.argsort", "numpy.append", "numpy.putmask", "numpy.sort", "numpy.iterable", "numpy.isinf", "numpy.linspace", "numpy.diff", "numpy.asanyarray", "numpy.nonzero", "numpy.atleast_1d", "numpy.issubdtype", "numpy.prod", "numpy.int64", "numpy.log", "numpy.modf", "numpy.around", "numpy.floor", "numpy.log10"], "warnings": ["warnings.warn", "warnings.catch_warnings", "warnings.filterwarnings"], "itertools": ["itertools.islice", "itertools.groupby", "itertools.zip_longest"], "os": ["os.path.dirname", "os.path.join"], "inspect": ["inspect.currentframe", "inspect.getfile", "inspect.signature"], "csv": ["csv.list_dialects", "csv.get_dialect"], "sys": ["sys.getfilesystemencoding"], "dataclasses": ["dataclasses.is_dataclass"], "weakref": ["weakref.ref"], "pandas": ["pandas._libs.tslibs.timedeltas.array_to_timedelta64", "pandas._libs.internals.BlockPlacement", "pandas._libs.tslibs.timedeltas.parse_timedelta_unit", "pandas._libs.tslibs.conversion.precision_from_unit", "pandas._libs.join.outer_join_indexer", "pandas._libs.missing.checknull", "pandas._libs.missing.is_matching_na", "pandas._libs.missing.isnaobj", "pandas._libs.join.inner_join_indexer", "pandas._libs.missing.isnaobj2d", "pandas._libs.lib.infer_dtype"], "pytz": ["pytz.UnknownTimeZoneError"], "copy": ["copy.deepcopy"], "gc": ["gc.get_referents"]}