{"<builtin>": ["<builtin>.len", "<builtin>.list", "<builtin>.enumerate", "<builtin>.sum", "<builtin>.range", "<builtin>.min", "<builtin>.zip", "<builtin>.ValueError", "<builtin>.set", "<builtin>.next", "<builtin>.sorted", "<builtin>.isinstance", "<builtin>.dict", "<builtin>.all", "<builtin>.max", "<builtin>.hasattr", "<builtin>.TypeError", "<builtin>.type", "<builtin>.frozenset", "<builtin>.super", "<builtin>.hash", "<builtin>.AssertionError"], "collections": ["collections.defaultdict", "collections.Counter", "collections.Counter.values", "collections.Counter.items"], "warnings": ["warnings.warn"], "itertools": ["itertools.count"], "heapq": ["heapq.heapify"]}